tavily/__init__.py
tavily/async_tavily.py
tavily/config.py
tavily/errors.py
tavily/tavily.py
tavily/utils.py
tavily/hybrid_rag/__init__.py
tavily/hybrid_rag/hybrid_rag.py
tavily_python-0.7.16.dist-info/licenses/LICENSE
tavily_python-0.7.16.dist-info/METADATA
tavily_python-0.7.16.dist-info/WHEEL
tavily_python-0.7.16.dist-info/top_level.txt
tavily_python-0.7.16.dist-info/RECORD
