Metadata-Version: 2.4
Name: tavily-python
Version: 0.7.16
Summary: Python wrapper for the Tavily API
Home-page: https://github.com/tavily-ai/tavily-python
Author: Tavily AI
Author-email: support@tavily.com
Classifier: Programming Language :: Python :: 3
Classifier: License :: OSI Approved :: MIT License
Classifier: Operating System :: OS Independent
Requires-Python: >=3.8
License-File: LICENSE
Requires-Dist: requests
Requires-Dist: tiktoken>=0.5.1
Requires-Dist: httpx
Dynamic: author
Dynamic: author-email
Dynamic: classifier
Dynamic: description
Dynamic: description-content-type
Dynamic: home-page
Dynamic: license-file
Dynamic: requires-dist
Dynamic: requires-python
Dynamic: summary
